transformation_tree/__init__.py
transformation_tree/__main__.py
transformation_tree/forecasting.py
transformation_tree/preprocessing.py
transformation_tree/stats_and_vis.py
transformation_tree/tree.py
transformation_tree/tests/__init__.py
transformation_tree/tests/addnodes_test.py
transformation_tree/tests/path_test.py
transformation_tree/tests/testops.py
transformation_tree/tests/tree_test_cases.py
transformation_tree/tests/ttree_helpers_test.py
transformation_tree-1.2.2.dist-info/METADATA
transformation_tree-1.2.2.dist-info/WHEEL
transformation_tree-1.2.2.dist-info/top_level.txt
transformation_tree-1.2.2.dist-info/RECORD
