Metadata-Version: 2.1
Name: transformation-tree
Version: 1.2.2
Summary: Transformation Tree library developed for CIS 422 @                  University of Oregon
Home-page: https://github.com/Sephta/time-series-modeling
Author: Seth Tal, Alec Springel, Ronny Fuentes, Stephanie Schofield, Kyra             Novitzky
License: UNKNOWN
Platform: UNKNOWN
Requires-Python: >=3.7.9
Requires-Dist: scikit-learn
Requires-Dist: anytree
Requires-Dist: pickle-mixin
Requires-Dist: pandas
Requires-Dist: numpy
Requires-Dist: scipy
Requires-Dist: statsmodels
Requires-Dist: seaborn
Requires-Dist: matplotlib
